{
  "file_number": 60,
  "time": "20221116T092003+09:00",
  "data": [
    {
      "id": 43,
      "value": 17
    },
    {
      "id": 9,
      "value": 70
    },
    {
      "id": 9,
      "value": 40
    },
    {
      "id": 943,
      "value": 32
    },
    {
      "id": 515,
      "value": 74
    },
    {
      "id": 769,
      "value": 46
    },
    {
      "id": 367,
      "value": 50
    },
    {
      "id": 143,
      "value": 65
    },
    {
      "id": 623,
      "value": 98
    },
    {
      "id": 912,
      "value": 94
    },
    {
      "id": 119,
      "value": 21
    },
    {
      "id": 772,
      "value": 44
    },
    {
      "id": 26,
      "value": 89
    },
    {
      "id": 174,
      "value": 2
    },
    {
      "id": 886,
      "value": 43
    },
    {
      "id": 621,
      "value": 36
    },
    {
      "id": 63,
      "value": 69
    },
    {
      "id": 980,
      "value": 68
    },
    {
      "id": 241,
      "value": 42
    },
    {
      "id": 828,
      "value": 37
    },
    {
      "id": 100,
      "value": 26
    },
    {
      "id": 930,
      "value": 11
    },
    {
      "id": 707,
      "value": 89
    },
    {
      "id": 379,
      "value": 96
    },
    {
      "id": 930,
      "value": 27
    },
    {
      "id": 593,
      "value": 46
    },
    {
      "id": 860,
      "value": 34
    },
    {
      "id": 70,
      "value": 94
    },
    {
      "id": 579,
      "value": 44
    },
    {
      "id": 510,
      "value": 29
    },
    {
      "id": 565,
      "value": 42
    },
    {
      "id": 293,
      "value": 39
    },
    {
      "id": 899,
      "value": 85
    },
    {
      "id": 526,
      "value": 14
    },
    {
      "id": 775,
      "value": 72
    },
    {
      "id": 672,
      "value": 33
    },
    {
      "id": 773,
      "value": 81
    },
    {
      "id": 373,
      "value": 13
    },
    {
      "id": 260,
      "value": 15
    },
    {
      "id": 341,
      "value": 87
    },
    {
      "id": 991,
      "value": 81
    },
    {
      "id": 310,
      "value": 91
    },
    {
      "id": 727,
      "value": 89
    },
    {
      "id": 987,
      "value": 10
    },
    {
      "id": 307,
      "value": 21
    },
    {
      "id": 206,
      "value": 74
    },
    {
      "id": 456,
      "value": 54
    },
    {
      "id": 777,
      "value": 77
    },
    {
      "id": 965,
      "value": 70
    },
    {
      "id": 501,
      "value": 81
    }
  ]
}