{
  "current_data": "dataset_45.json",
  "before_data": "dataset_44.json",
  "data": [
    {
      "id": 25,
      "value": 6,
      "before_value": 55,
      "delta": -49
    },
    {
      "id": 27,
      "value": 20,
      "before_value": 31,
      "delta": -11
    },
    {
      "id": 41,
      "value": 28,
      "before_value": 41,
      "delta": -13
    },
    {
      "id": 50,
      "value": 25,
      "before_value": 95,
      "delta": 25
    },
    {
      "id": 61,
      "value": 24,
      "before_value": 20,
      "delta": 24
    },
    {
      "id": 78,
      "value": 60,
      "before_value": 47,
      "delta": 60
    },
    {
      "id": 107,
      "value": 91,
      "before_value": 65,
      "delta": 91
    },
    {
      "id": 108,
      "value": 69,
      "before_value": 79,
      "delta": 69
    },
    {
      "id": 120,
      "value": 64,
      "before_value": 91,
      "delta": 64
    },
    {
      "id": 140,
      "value": 98,
      "before_value": 45,
      "delta": 98
    },
    {
      "id": 150,
      "value": 63,
      "before_value": 28,
      "delta": 63
    },
    {
      "id": 177,
      "value": 73,
      "before_value": 78,
      "delta": 73
    },
    {
      "id": 202,
      "value": 6,
      "before_value": 65,
      "delta": 6
    },
    {
      "id": 208,
      "value": 47,
      "before_value": 6,
      "delta": 47
    },
    {
      "id": 250,
      "value": 21,
      "before_value": 98,
      "delta": 21
    },
    {
      "id": 263,
      "value": 29,
      "before_value": 58,
      "delta": 29
    },
    {
      "id": 306,
      "value": 16,
      "before_value": 76,
      "delta": 16
    },
    {
      "id": 318,
      "value": 31,
      "before_value": 15,
      "delta": 31
    },
    {
      "id": 360,
      "value": 77,
      "before_value": 41,
      "delta": 77
    },
    {
      "id": 365,
      "value": 45,
      "before_value": 83,
      "delta": 45
    },
    {
      "id": 378,
      "value": 22,
      "before_value": 95,
      "delta": 22
    },
    {
      "id": 450,
      "value": 89,
      "before_value": 3,
      "delta": 89
    },
    {
      "id": 450,
      "value": 22,
      "before_value": 54,
      "delta": 22
    },
    {
      "id": 452,
      "value": 89,
      "before_value": 34,
      "delta": 89
    },
    {
      "id": 456,
      "value": 13,
      "before_value": 49,
      "delta": 13
    },
    {
      "id": 472,
      "value": 91,
      "before_value": 91,
      "delta": 91
    },
    {
      "id": 553,
      "value": 45,
      "before_value": 88,
      "delta": 45
    },
    {
      "id": 559,
      "value": 56,
      "before_value": 46,
      "delta": 56
    },
    {
      "id": 670,
      "value": 32,
      "before_value": 75,
      "delta": 32
    },
    {
      "id": 722,
      "value": 25,
      "before_value": 35,
      "delta": 25
    },
    {
      "id": 726,
      "value": 90,
      "before_value": 42,
      "delta": 90
    },
    {
      "id": 743,
      "value": 0,
      "before_value": 57,
      "delta": 0
    },
    {
      "id": 758,
      "value": 42,
      "before_value": 62,
      "delta": 42
    },
    {
      "id": 759,
      "value": 78,
      "before_value": 63,
      "delta": 78
    },
    {
      "id": 785,
      "value": 87,
      "before_value": 34,
      "delta": 87
    },
    {
      "id": 794,
      "value": 42,
      "before_value": 49,
      "delta": 42
    },
    {
      "id": 808,
      "value": 94,
      "before_value": 23,
      "delta": 94
    },
    {
      "id": 813,
      "value": 8,
      "before_value": 60,
      "delta": 8
    },
    {
      "id": 816,
      "value": 74,
      "before_value": 1,
      "delta": 74
    },
    {
      "id": 825,
      "value": 5,
      "before_value": 30,
      "delta": 5
    },
    {
      "id": 836,
      "value": 5,
      "before_value": 16,
      "delta": 5
    },
    {
      "id": 837,
      "value": 49,
      "before_value": 75,
      "delta": 49
    },
    {
      "id": 848,
      "value": 80,
      "before_value": 61,
      "delta": 80
    },
    {
      "id": 878,
      "value": 58,
      "before_value": 70,
      "delta": 58
    },
    {
      "id": 889,
      "value": 73,
      "before_value": 21,
      "delta": 73
    },
    {
      "id": 900,
      "value": 3,
      "before_value": 66,
      "delta": 3
    },
    {
      "id": 904,
      "value": 58,
      "before_value": 22,
      "delta": 58
    },
    {
      "id": 954,
      "value": 32,
      "before_value": 44,
      "delta": 32
    },
    {
      "id": 966,
      "value": 34,
      "before_value": 59,
      "delta": 34
    },
    {
      "id": 977,
      "value": 10,
      "before_value": 61,
      "delta": 10
    }
  ]
}