{
  "current_data": "dataset_35.json",
  "before_data": "dataset_34.json",
  "data": [
    {
      "id": 4,
      "value": 34,
      "before_value": 52,
      "delta": -18
    },
    {
      "id": 80,
      "value": 77,
      "before_value": 50,
      "delta": 77
    },
    {
      "id": 98,
      "value": 15,
      "before_value": 32,
      "delta": 15
    },
    {
      "id": 108,
      "value": 97,
      "before_value": 65,
      "delta": 97
    },
    {
      "id": 113,
      "value": 17,
      "before_value": 11,
      "delta": 17
    },
    {
      "id": 118,
      "value": 51,
      "before_value": 57,
      "delta": 51
    },
    {
      "id": 187,
      "value": 55,
      "before_value": 19,
      "delta": 55
    },
    {
      "id": 235,
      "value": 82,
      "before_value": 87,
      "delta": 82
    },
    {
      "id": 252,
      "value": 61,
      "before_value": 17,
      "delta": 61
    },
    {
      "id": 268,
      "value": 98,
      "before_value": 17,
      "delta": 98
    },
    {
      "id": 296,
      "value": 96,
      "before_value": 53,
      "delta": 96
    },
    {
      "id": 323,
      "value": 75,
      "before_value": 17,
      "delta": 75
    },
    {
      "id": 327,
      "value": 19,
      "before_value": 14,
      "delta": 19
    },
    {
      "id": 329,
      "value": 7,
      "before_value": 52,
      "delta": 7
    },
    {
      "id": 332,
      "value": 8,
      "before_value": 40,
      "delta": 8
    },
    {
      "id": 335,
      "value": 17,
      "before_value": 24,
      "delta": 17
    },
    {
      "id": 370,
      "value": 80,
      "before_value": 5,
      "delta": 80
    },
    {
      "id": 393,
      "value": 2,
      "before_value": 92,
      "delta": 2
    },
    {
      "id": 425,
      "value": 37,
      "before_value": 10,
      "delta": 37
    },
    {
      "id": 427,
      "value": 58,
      "before_value": 19,
      "delta": 58
    },
    {
      "id": 436,
      "value": 13,
      "before_value": 25,
      "delta": 13
    },
    {
      "id": 461,
      "value": 9,
      "before_value": 16,
      "delta": 9
    },
    {
      "id": 474,
      "value": 67,
      "before_value": 68,
      "delta": 67
    },
    {
      "id": 487,
      "value": 70,
      "before_value": 44,
      "delta": 70
    },
    {
      "id": 491,
      "value": 84,
      "before_value": 90,
      "delta": 84
    },
    {
      "id": 495,
      "value": 10,
      "before_value": 3,
      "delta": 10
    },
    {
      "id": 513,
      "value": 98,
      "before_value": 61,
      "delta": 98
    },
    {
      "id": 517,
      "value": 30,
      "before_value": 22,
      "delta": 30
    },
    {
      "id": 546,
      "value": 31,
      "before_value": 83,
      "delta": 31
    },
    {
      "id": 550,
      "value": 21,
      "before_value": 29,
      "delta": 21
    },
    {
      "id": 665,
      "value": 37,
      "before_value": 99,
      "delta": 37
    },
    {
      "id": 690,
      "value": 84,
      "before_value": 7,
      "delta": 84
    },
    {
      "id": 739,
      "value": 74,
      "before_value": 83,
      "delta": 74
    },
    {
      "id": 753,
      "value": 31,
      "before_value": 60,
      "delta": 31
    },
    {
      "id": 761,
      "value": 72,
      "before_value": 75,
      "delta": 72
    },
    {
      "id": 766,
      "value": 13,
      "before_value": 14,
      "delta": 13
    },
    {
      "id": 792,
      "value": 40,
      "before_value": 95,
      "delta": 40
    },
    {
      "id": 803,
      "value": 22,
      "before_value": 56,
      "delta": 22
    },
    {
      "id": 809,
      "value": 26,
      "before_value": 37,
      "delta": 26
    },
    {
      "id": 827,
      "value": 22,
      "before_value": 72,
      "delta": 22
    },
    {
      "id": 830,
      "value": 98,
      "before_value": 31,
      "delta": 98
    },
    {
      "id": 859,
      "value": 29,
      "before_value": 5,
      "delta": 29
    },
    {
      "id": 927,
      "value": 15,
      "before_value": 61,
      "delta": 15
    },
    {
      "id": 932,
      "value": 68,
      "before_value": 22,
      "delta": 68
    },
    {
      "id": 935,
      "value": 87,
      "before_value": 79,
      "delta": 87
    },
    {
      "id": 954,
      "value": 99,
      "before_value": 44,
      "delta": 99
    },
    {
      "id": 968,
      "value": 45,
      "before_value": 66,
      "delta": 45
    },
    {
      "id": 975,
      "value": 4,
      "before_value": 4,
      "delta": 4
    },
    {
      "id": 978,
      "value": 32,
      "before_value": 59,
      "delta": 32
    },
    {
      "id": 999,
      "value": 34,
      "before_value": 61,
      "delta": 34
    }
  ]
}