{
  "current_data": "dataset_1.json",
  "before_data": "dataset_0.json",
  "data": [
    {
      "id": 34,
      "value": 34,
      "before_value": 3,
      "delta": 31
    },
    {
      "id": 72,
      "value": 50,
      "before_value": 14,
      "delta": 50
    },
    {
      "id": 83,
      "value": 59,
      "before_value": 50,
      "delta": 59
    },
    {
      "id": 93,
      "value": 76,
      "before_value": 23,
      "delta": 76
    },
    {
      "id": 113,
      "value": 34,
      "before_value": 73,
      "delta": 34
    },
    {
      "id": 154,
      "value": 3,
      "before_value": 20,
      "delta": 3
    },
    {
      "id": 217,
      "value": 32,
      "before_value": 46,
      "delta": 32
    },
    {
      "id": 223,
      "value": 34,
      "before_value": 27,
      "delta": 34
    },
    {
      "id": 238,
      "value": 87,
      "before_value": 5,
      "delta": 87
    },
    {
      "id": 241,
      "value": 42,
      "before_value": 16,
      "delta": 42
    },
    {
      "id": 260,
      "value": 94,
      "before_value": 34,
      "delta": 94
    },
    {
      "id": 292,
      "value": 57,
      "before_value": 40,
      "delta": 57
    },
    {
      "id": 293,
      "value": 0,
      "before_value": 66,
      "delta": 0
    },
    {
      "id": 305,
      "value": 7,
      "before_value": 40,
      "delta": 7
    },
    {
      "id": 325,
      "value": 79,
      "before_value": 24,
      "delta": 79
    },
    {
      "id": 345,
      "value": 12,
      "before_value": 7,
      "delta": 12
    },
    {
      "id": 352,
      "value": 31,
      "before_value": 94,
      "delta": 31
    },
    {
      "id": 368,
      "value": 29,
      "before_value": 73,
      "delta": 29
    },
    {
      "id": 404,
      "value": 27,
      "before_value": 10,
      "delta": 27
    },
    {
      "id": 465,
      "value": 6,
      "before_value": 97,
      "delta": 6
    },
    {
      "id": 472,
      "value": 80,
      "before_value": 59,
      "delta": 80
    },
    {
      "id": 476,
      "value": 57,
      "before_value": 21,
      "delta": 57
    },
    {
      "id": 514,
      "value": 58,
      "before_value": 81,
      "delta": 58
    },
    {
      "id": 558,
      "value": 77,
      "before_value": 73,
      "delta": 77
    },
    {
      "id": 559,
      "value": 47,
      "before_value": 49,
      "delta": 47
    },
    {
      "id": 563,
      "value": 87,
      "before_value": 15,
      "delta": 87
    },
    {
      "id": 586,
      "value": 40,
      "before_value": 37,
      "delta": 40
    },
    {
      "id": 601,
      "value": 36,
      "before_value": 99,
      "delta": 36
    },
    {
      "id": 611,
      "value": 45,
      "before_value": 90,
      "delta": 45
    },
    {
      "id": 616,
      "value": 55,
      "before_value": 29,
      "delta": 55
    },
    {
      "id": 631,
      "value": 98,
      "before_value": 72,
      "delta": 98
    },
    {
      "id": 635,
      "value": 97,
      "before_value": 7,
      "delta": 97
    },
    {
      "id": 645,
      "value": 44,
      "before_value": 82,
      "delta": 44
    },
    {
      "id": 651,
      "value": 47,
      "before_value": 48,
      "delta": 47
    },
    {
      "id": 661,
      "value": 33,
      "before_value": 82,
      "delta": 33
    },
    {
      "id": 674,
      "value": 21,
      "before_value": 17,
      "delta": 21
    },
    {
      "id": 675,
      "value": 9,
      "before_value": 5,
      "delta": 9
    },
    {
      "id": 685,
      "value": 44,
      "before_value": 26,
      "delta": 44
    },
    {
      "id": 707,
      "value": 40,
      "before_value": 73,
      "delta": 40
    },
    {
      "id": 721,
      "value": 27,
      "before_value": 1,
      "delta": 27
    },
    {
      "id": 722,
      "value": 52,
      "before_value": 42,
      "delta": 52
    },
    {
      "id": 775,
      "value": 34,
      "before_value": 58,
      "delta": 34
    },
    {
      "id": 855,
      "value": 18,
      "before_value": 55,
      "delta": 18
    },
    {
      "id": 899,
      "value": 99,
      "before_value": 61,
      "delta": 99
    },
    {
      "id": 912,
      "value": 10,
      "before_value": 34,
      "delta": 10
    },
    {
      "id": 941,
      "value": 34,
      "before_value": 56,
      "delta": 34
    },
    {
      "id": 946,
      "value": 30,
      "before_value": 94,
      "delta": 30
    },
    {
      "id": 952,
      "value": 25,
      "before_value": 26,
      "delta": 25
    },
    {
      "id": 958,
      "value": 25,
      "before_value": 72,
      "delta": 25
    },
    {
      "id": 976,
      "value": 59,
      "before_value": 24,
      "delta": 59
    }
  ]
}